dfrost/cli.py
dfrost/lib/command.py
dfrost/lib/compress.py
dfrost/lib/config.py
dfrost/lib/log.py
dfrost/lib/s3.py
dfrost/lib/temp.py
dfrost/pull.py
dfrost/push.py
dfrost-0.1.8.dist-info/entry_points.txt
dfrost-0.1.8.dist-info/WHEEL
dfrost-0.1.8.dist-info/METADATA
dfrost-0.1.8.dist-info/RECORD
